kSpider_internal.py
_kSpider_internal.cpython-310-x86_64-linux-gnu.so
DBRetina-2.2.11.dist-info/top_level.txt
DBRetina-2.2.11.dist-info/LICENSE
DBRetina-2.2.11.dist-info/RECORD
DBRetina-2.2.11.dist-info/WHEEL
DBRetina-2.2.11.dist-info/METADATA
DBRetina-2.2.11.dist-info/entry_points.txt
internal/__init__.py
kSpider2/kSpider_main.py
kSpider2/ks_clustering.py
kSpider2/ks_pairwise.py
kSpider2/ks_index.py
kSpider2/ks_sketch_dbretina.py
kSpider2/ks_dedup.py
kSpider2/ks_query_dbretina.py
kSpider2/ks_bipartite_pairwise.py
kSpider2/ks_modularity_scan.py
kSpider2/customLogger.py
kSpider2/ks_filter.py
kSpider2/ks_interactome.py
kSpider2/ks_setcov.py
kSpider2/ks_export.py
kSpider2/kSpider_version.py
kSpider2/ks_clustmap.py
kSpider2/click_context.py
kSpider2/dbretina_doc_url.py
kSpider2/BAK_ks_dedup_cpp.py
kSpider2/__init__.py
kSpider2/ks_fastx_to_kfs.py
kSpider2/ks_dataset_indexing.py
DBRetina.libs/libbz2-a273e504.so.1.0.6
DBRetina.libs/libgomp-a34b3233.so.1.0.0
